BuzzerboyArchetypeStack/BuzzerboyArchetype.py
BuzzerboyArchetypeStack/__init__.py
buzzerboyarchetype-1.10.4.dist-info/METADATA
buzzerboyarchetype-1.10.4.dist-info/WHEEL
buzzerboyarchetype-1.10.4.dist-info/top_level.txt
buzzerboyarchetype-1.10.4.dist-info/RECORD
