Metadata-Version: 2.4
Name: BuzzerboyArchetype
Version: 1.10.4
Summary: Buzzerboy Architecture Standard for Buzzerboy Based Architectures
Home-page: https://www.buzzerboy.com/
Author: Buzzerboy Inc
Author-email: Buzzerboy Inc <info@buzzerboy.com>
Project-URL: Homepage, https://www.buzzerboy.com/
Project-URL: Issues, https://dev.azure.com/buzzerboyinc/buzzerboy
Classifier: Programming Language :: Python :: 3
Classifier: License :: OSI Approved :: MIT License
Classifier: Operating System :: OS Independent
Requires-Python: >=3.8
Dynamic: author
Dynamic: home-page
Dynamic: requires-python
